bimcvcovid19i/__init__.py
bimcvcovid19i/__init__.pyi
bimcvcovid19i/__version__.py
bimcvcovid19i/__version__.pyi
bimcvcovid19i/assets.py
bimcvcovid19i/assets.pyi
bimcvcovid19i/data.py
bimcvcovid19i/data.pyi
bimcvcovid19i/interface.py
bimcvcovid19i/interface.pyi
bimcvcovid19i/postprocessing.py
bimcvcovid19i/postprocessing.pyi
bimcvcovid19i/py.typed
bimcvcovid19i/tools.py
bimcvcovid19i/tools.pyi
bimcvcovid19i/typing.py
bimcvcovid19i/typing.pyi
bimcvcovid19i/webdav.py
bimcvcovid19i/webdav.pyi
bimcvcovid19i-0.1.2.dist-info/LICENSE
bimcvcovid19i-0.1.2.dist-info/METADATA
bimcvcovid19i-0.1.2.dist-info/WHEEL
bimcvcovid19i-0.1.2.dist-info/top_level.txt
bimcvcovid19i-0.1.2.dist-info/RECORD
