Metadata-Version: 2.1
Name: bimcvcovid19i
Version: 0.1.2
Summary: Interface for working with BIMCV COVID 19 dataset
Home-page: https://github.com/rilshok/BIMCV-COVID-19-interface
Author: Vladislav A. Proskurov
Author-email: rilshok@pm.me
License: MIT
Classifier: Programming Language :: Python :: 3.9
Classifier: License :: OSI Approved :: MIT License
Classifier: Operating System :: OS Independent
Classifier: Development Status :: 1 - Planning
Requires-Python: >=3.9
License-File: LICENSE
Requires-Dist: webdavclient3
Requires-Dist: SimpleITK
Requires-Dist: numpy
Requires-Dist: nibabel
Requires-Dist: deli
Requires-Dist: tqdm
Requires-Dist: pandas
Requires-Dist: pydicom
Requires-Dist: scipy
